continuous_grid_world/__init__.py
continuous_grid_world/radial_basis_function_2D.py
continuous_grid_world/envs/__init__.py
continuous_grid_world/envs/continuous_grid_world.py
continuous_grid_world/envs/radial_basis_function_2D.py
continuous_grid_world-0.0.6.dist-info/METADATA
continuous_grid_world-0.0.6.dist-info/WHEEL
continuous_grid_world-0.0.6.dist-info/top_level.txt
continuous_grid_world-0.0.6.dist-info/RECORD
