Metadata-Version: 2.1
Name: continuous-grid-world
Version: 0.0.6
Summary: Grid World with continuous action spaces
Home-page: UNKNOWN
Author: Christoper Glenn Wulur
Author-email: christoper.glennwu@gmail.com
License: UNKNOWN
Platform: UNKNOWN
Requires-Dist: gym
